pr_commenter.py
pr_commenter-0.2.4.dist-info/entry_points.txt
pr_commenter-0.2.4.dist-info/licenses/LICENSE
pr_commenter-0.2.4.dist-info/WHEEL
pr_commenter-0.2.4.dist-info/METADATA
pr_commenter-0.2.4.dist-info/RECORD
