Metadata-Version: 2.4
Name: pr-commenter
Version: 0.2.4
Summary: Create and manage automatic comments in a Github PR
Author-email: Martín Gaitán <marting@shiphero.com>
Requires-Python: >=3.7
Classifier: Programming Language :: Python :: 3
Classifier: Development Status :: 4 - Beta
Classifier: Environment :: Console
Classifier: Intended Audience :: Developers
Classifier: License :: OSI Approved :: BSD License
Classifier: Topic :: Communications
Classifier: Topic :: Software Development :: Build Tools
License-File: LICENSE
Requires-Dist: pygithub >= 1.55
Requires-Dist: docopt-ng >= 0.8.1
Requires-Dist: Jinja2 >= 3
Requires-Dist: pytest ; extra == "dev"
Requires-Dist: pytest-mock ; extra == "dev"
Requires-Dist: black ; extra == "dev"
Requires-Dist: rich ; extra == "dev"
Project-URL: Changelog, https://github.com/Shiphero/pr-commenter/blob/main/CHANGELOG.md
Project-URL: Home, https://github.com/Shiphero/pr-commenter
Provides-Extra: dev
